biofluff-2.1.4.data/scripts/fluff
biofluff-2.1.4.data/scripts/fluff_bandplot.py
biofluff-2.1.4.data/scripts/fluff_heatmap.py
biofluff-2.1.4.data/scripts/fluff_profile.py
biofluff-2.1.4.dist-info/DESCRIPTION.rst
biofluff-2.1.4.dist-info/METADATA
biofluff-2.1.4.dist-info/RECORD
biofluff-2.1.4.dist-info/WHEEL
biofluff-2.1.4.dist-info/metadata.json
biofluff-2.1.4.dist-info/top_level.txt
fluff/__init__.py
fluff/color.py
fluff/config.py
fluff/fluffio.py
fluff/parse.py
fluff/plot.py
fluff/track.py
fluff/util.py
fluff/commands/__init__.py
fluff/commands/bandplot.py
fluff/commands/heatmap.py
fluff/commands/profile.py
